cbe_verify/__init__.py
cbe_verify/cbe.py
cbe_verify/models.py
cbe_verify-0.1.1.dist-info/METADATA
cbe_verify-0.1.1.dist-info/WHEEL
cbe_verify-0.1.1.dist-info/top_level.txt
cbe_verify-0.1.1.dist-info/RECORD
