Metadata-Version: 2.4
Name: cbe-verify
Version: 0.1.1
Summary: A simple package to verify CBE payment receipts
Home-page: https://github.com/yohaboy/cbe_verifier
Author: yohnnes gizaw
Author-email: yohnnesgizaw777@example.com
Classifier: Programming Language :: Python :: 3
Classifier: License :: OSI Approved :: MIT License
Classifier: Operating System :: OS Independent
Requires-Python: >=3.7
Requires-Dist: requests>=2.25.1
Requires-Dist: pdfplumber>=0.7.4
Dynamic: author
Dynamic: author-email
Dynamic: classifier
Dynamic: description
Dynamic: description-content-type
Dynamic: home-page
Dynamic: requires-dist
Dynamic: requires-python
Dynamic: summary
